dqc/__init__.py
dqc/base.py
dqc/crossval.py
dqc/utils/__init__.py
dqc/utils/_generic.py
dqc/utils/_sklearn_artifacts.py
tests/__init__.py
tests/conftest.py
tests/test_crossval.py
c2_4apr24-0.1.2.dist-info/LICENSE
c2_4apr24-0.1.2.dist-info/METADATA
c2_4apr24-0.1.2.dist-info/WHEEL
c2_4apr24-0.1.2.dist-info/top_level.txt
c2_4apr24-0.1.2.dist-info/RECORD
