Metadata-Version: 2.1
Name: c2-4apr24
Version: 0.1.2
Summary: Data Quality Check for Machine Learning
Home-page: https://github.com/sumanthprabhu/C2
Author: Sumanth S Prabhu
Author-email: Sumanth S Prabhu <sumanthprabhu.104@gmail.com>
License: MIT License
Project-URL: Homepage, https://github.com/sumanthprabhu/C2
Project-URL: Source, https://github.com/sumanthprabhu/C2
Project-URL: Tracker, https://github.com/sumanthprabhu/C2/issues
Keywords: nlp,data curation,machine learning
Classifier: Intended Audience :: Developers
Classifier: Intended Audience :: Education
Classifier: Intended Audience :: Science/Research
Classifier: License :: OSI Approved :: MIT License
Classifier: Operating System :: MacOS
Classifier: Operating System :: POSIX
Classifier: Operating System :: Unix
Classifier: Programming Language :: Python :: 3
Classifier: Programming Language :: Python :: 3.9
Classifier: Programming Language :: Python :: 3.10
Classifier: Topic :: Scientific/Engineering :: Artificial Intelligence
Requires-Python: >=3.9
License-File: LICENSE
Requires-Dist: transformers >=4.39
Requires-Dist: datasets >=2.18
Requires-Dist: scikit-learn >=1.3.2
Requires-Dist: ruff >=0.3.4
Provides-Extra: test
Requires-Dist: pytest >=8.1.1 ; extra == 'test'
